wonambi/VERSION
wonambi/__init__.py
wonambi/dataset.py
wonambi/datatype.py
wonambi/graphoelement.py
wonambi/attr/__init__.py
wonambi/attr/anat.py
wonambi/attr/annotations.py
wonambi/attr/chan.py
wonambi/bids/__init__.py
wonambi/bids/find.py
wonambi/bids/structure.py
wonambi/bids/utils.py
wonambi/bin/__init__.py
wonambi/bin/convert.py
wonambi/bin/scroll_data.py
wonambi/detect/__init__.py
wonambi/detect/agreement.py
wonambi/detect/arousal.py
wonambi/detect/ripple.py
wonambi/detect/slowwave.py
wonambi/detect/spindle.py
wonambi/ioeeg/__init__.py
wonambi/ioeeg/abf.py
wonambi/ioeeg/bci2000.py
wonambi/ioeeg/bids.py
wonambi/ioeeg/blackrock.py
wonambi/ioeeg/brainvision.py
wonambi/ioeeg/edf.py
wonambi/ioeeg/eeglab.py
wonambi/ioeeg/egimff.py
wonambi/ioeeg/fieldtrip.py
wonambi/ioeeg/ktlx.py
wonambi/ioeeg/lyonrri.py
wonambi/ioeeg/micromed.py
wonambi/ioeeg/mnefiff.py
wonambi/ioeeg/moberg.py
wonambi/ioeeg/openephys.py
wonambi/ioeeg/text.py
wonambi/ioeeg/utils.py
wonambi/ioeeg/wonambi.py
wonambi/source/__init__.py
wonambi/source/linear.py
wonambi/source/morph.py
wonambi/trans/__init__.py
wonambi/trans/analyze.py
wonambi/trans/baseline.py
wonambi/trans/filter.py
wonambi/trans/frequency.py
wonambi/trans/math.py
wonambi/trans/merge.py
wonambi/trans/montage.py
wonambi/trans/peaks.py
wonambi/trans/reject.py
wonambi/trans/select.py
wonambi/trans/extern/__init__.py
wonambi/trans/extern/dpss.py
wonambi/utils/__init__.py
wonambi/utils/exceptions.py
wonambi/utils/simulate.py
wonambi/viz/__init__.py
wonambi/viz/base.py
wonambi/viz/plot_3d.py
wonambi/viz/visuals.py
wonambi/widgets/__init__.py
wonambi/widgets/analysis.py
wonambi/widgets/channels.py
wonambi/widgets/creation.py
wonambi/widgets/detect_dialogs.py
wonambi/widgets/info.py
wonambi/widgets/labels.py
wonambi/widgets/modal_widgets.py
wonambi/widgets/notes.py
wonambi/widgets/overview.py
wonambi/widgets/settings.py
wonambi/widgets/spectrum.py
wonambi/widgets/traces.py
wonambi/widgets/utils.py
wonambi/widgets/video.py
wonambi-7.15.dist-info/LICENSE
wonambi-7.15.dist-info/METADATA
wonambi-7.15.dist-info/WHEEL
wonambi-7.15.dist-info/entry_points.txt
wonambi-7.15.dist-info/top_level.txt
wonambi-7.15.dist-info/RECORD
