Metadata-Version: 2.1
Name: wonambi
Version: 7.15
Summary: Tools for EEG, ECoG, iEEG, especially for sleep
Home-page: https://github.com/wonambi-python/wonambi
Author: Gio Piantoni / Jordan O'Byrne
Author-email: wonambi@gpiantoni.com
License: GPLv3
Keywords: neuroscience analysis sleep EEG ECoG
Classifier: Development Status :: 4 - Beta
Classifier: Environment :: X11 Applications :: Qt
Classifier: Intended Audience :: Healthcare Industry
Classifier: Intended Audience :: Science/Research
Classifier: Topic :: Scientific/Engineering :: Bio-Informatics
Classifier: Topic :: Scientific/Engineering :: Medical Science Apps.
Classifier: Topic :: Scientific/Engineering :: Visualization
Classifier: License :: OSI Approved :: BSD License
Classifier: Programming Language :: Python :: 3 :: Only
Classifier: Programming Language :: Python :: 3.6
Classifier: Programming Language :: Python :: 3.7
License-File: LICENSE
Requires-Dist: numpy
Requires-Dist: scipy
Provides-Extra: all
Requires-Dist: pyqt5 ; extra == 'all'
Requires-Dist: python-vlc ; extra == 'all'
Requires-Dist: vispy ; extra == 'all'
Requires-Dist: h5py ; extra == 'all'
Requires-Dist: mne ; extra == 'all'
Requires-Dist: nibabel ; extra == 'all'
Requires-Dist: fooof ; extra == 'all'
Requires-Dist: tensorpac ==0.5.6 ; extra == 'all'
Provides-Extra: gui
Requires-Dist: pyqt5 ; extra == 'gui'
Provides-Extra: test
Requires-Dist: pytest ; extra == 'test'
Requires-Dist: pytest-qt ; extra == 'test'
Requires-Dist: pytest-cov ; extra == 'test'
Requires-Dist: codecov ; extra == 'test'
Requires-Dist: plotly ; extra == 'test'
Provides-Extra: viz
Requires-Dist: vispy ; extra == 'viz'
